skued/__init__.py
skued/__main__.py
skued/affine.py
skued/array_utils.py
skued/eproperties.py
skued/fft.py
skued/patterson.py
skued/plot_utils.py
skued/potential_map.py
skued/thin_films.py
skued/utils.py
skued/voigt.py
skued/baseline/__init__.py
skued/baseline/algorithms.py
skued/baseline/dtcwt.py
skued/baseline/data/qshift1.npz
skued/baseline/data/qshift2.npz
skued/baseline/data/qshift3.npz
skued/baseline/data/qshift4.npz
skued/baseline/data/qshift5.npz
skued/baseline/data/qshift6.npz
skued/baseline/tests/__init__.py
skued/baseline/tests/test_algorithms.py
skued/baseline/tests/test_dtcwt.py
skued/image/__init__.py
skued/image/alignment.py
skued/image/brillouin.py
skued/image/calibration.py
skued/image/center.py
skued/image/indexing.py
skued/image/metrics.py
skued/image/powder.py
skued/image/symmetry.py
skued/image/tests/__init__.py
skued/image/tests/test_alignment.py
skued/image/tests/test_brillouin.py
skued/image/tests/test_calibration.py
skued/image/tests/test_center.py
skued/image/tests/test_indexing.py
skued/image/tests/test_indexing_persistence.py
skued/image/tests/test_metrics.py
skued/image/tests/test_powder.py
skued/image/tests/test_symmetry.py
skued/io/__init__.py
skued/io/diffshow.py
skued/io/dm.py
skued/io/io.py
skued/io/merlin.py
skued/io/tests/__init__.py
skued/io/tests/test_io.py
skued/io/tests/data/bismuth.dm3
skued/io/tests/data/bismuth.dm4
skued/io/tests/data/png_test.png
skued/io/tests/data/test.mib
skued/io/tests/data/test_multi.mib
skued/simulation/__init__.py
skued/simulation/form_factors.py
skued/simulation/kinematic.py
skued/simulation/potential.py
skued/simulation/powdersim.py
skued/simulation/scattering_params.py
skued/simulation/structure_factors.py
skued/simulation/data/aspherical.yaml
skued/simulation/tests/__init__.py
skued/simulation/tests/test_kinematic.py
skued/simulation/tests/test_potential.py
skued/simulation/tests/test_powdersim.py
skued/simulation/tests/test_structure_factors.py
skued/tests/__init__.py
scikit_ued-2.1.17.dist-info/LICENSE.txt
scikit_ued-2.1.17.dist-info/METADATA
scikit_ued-2.1.17.dist-info/WHEEL
scikit_ued-2.1.17.dist-info/entry_points.txt
scikit_ued-2.1.17.dist-info/top_level.txt
scikit_ued-2.1.17.dist-info/RECORD
