Metadata-Version: 2.1
Name: scikit-ued
Version: 2.1.17
Summary: Collection of algorithms and functions for ultrafast electron scattering
Home-page: http://scikit-ued.readthedocs.io
Author: Laurent P. René de Cotret
Author-email: laurent.renedecotret@mail.mcgill.ca
Maintainer: Laurent P. René de Cotret
Maintainer-email: laurent.renedecotret@mail.mcgill.ca
License: GPLv3
Download-URL: http://github.com/LaurentRDC/scikit-ued
Project-URL: Documentation, https://scikit-ued.readthedocs.io/
Project-URL: Source, https://github.com/LaurentRDC/scikit-ued
Keywords: ultrafast electron scattering
Platform: UNKNOWN
Classifier: Environment :: Console
Classifier: Development Status :: 5 - Production/Stable
Classifier: Intended Audience :: Science/Research
Classifier: License :: OSI Approved :: GNU General Public License v3 (GPLv3)
Classifier: Natural Language :: English
Classifier: Operating System :: OS Independent
Classifier: Programming Language :: Python :: 3
Classifier: Topic :: Scientific/Engineering
Classifier: Topic :: Scientific/Engineering :: Physics
Requires-Python: >=3.7
License-File: LICENSE.txt
Requires-Dist: crystals <2,>=1.3.1
Requires-Dist: npstreams <2,>=1.6.5
Requires-Dist: numpy <2,>=1.17
Requires-Dist: pywavelets <2,>=1.0.0
Requires-Dist: scikit-image <1,>=0.19
Requires-Dist: scipy !=1.10.0,<2,>=1.5.0
Requires-Dist: pyyaml >=3.1
Requires-Dist: matplotlib <4,>=3.5
Provides-Extra: diffshow
Requires-Dist: pyqtgraph <1,>=0.12 ; extra == 'diffshow'
Requires-Dist: PyQt5 ; extra == 'diffshow'
